doit_progress.py
doit_progress-0.3.dist-info/licenses/LICENSE
doit_progress-0.3.dist-info/METADATA
doit_progress-0.3.dist-info/WHEEL
doit_progress-0.3.dist-info/entry_points.txt
doit_progress-0.3.dist-info/top_level.txt
doit_progress-0.3.dist-info/RECORD
