Metadata-Version: 2.4
Name: doit-progress
Version: 0.3
Summary: A doit command that displays the progress of tasks.
Author-email: Julien Pontabry <jpontabry@unistra.fr>
License: 
Keywords: doit,command
Classifier: Development Status :: 5 - Production/Stable
Classifier: Environment :: Console
Classifier: Intended Audience :: Developers
Classifier: Intended Audience :: Science/Research
Classifier: License :: CeCILL-B Free Software License Agreement (CECILL-B)
Classifier: Programming Language :: Python :: 3
Classifier: Programming Language :: Python :: 3.8
Classifier: Programming Language :: Python :: 3.9
Classifier: Programming Language :: Python :: 3.10
Classifier: Programming Language :: Python :: 3.11
Classifier: Programming Language :: Python :: 3 :: Only
Classifier: Topic :: Scientific/Engineering
Classifier: Topic :: Software Development :: Build Tools
Classifier: Topic :: Software Development :: Libraries :: Python Modules
Requires-Python: >=3.8
License-File: LICENSE
Requires-Dist: doit>=0.36.0
Requires-Dist: cloudpickle>=3.1.1
Requires-Dist: doit-sqlite-sync>=1.0
Dynamic: license-file
